speedtest_cloudflare_cli/__init__.py
speedtest_cloudflare_cli/main.py
speedtest_cloudflare_cli/core/__init__.py
speedtest_cloudflare_cli/core/dashboard.py
speedtest_cloudflare_cli/core/speedtest.py
speedtest_cloudflare_cli/models/__init__.py
speedtest_cloudflare_cli/models/metadata.py
speedtest_cloudflare_cli/models/result.py
speedtest_cloudflare_cli-0.2.2.dist-info/METADATA
speedtest_cloudflare_cli-0.2.2.dist-info/WHEEL
speedtest_cloudflare_cli-0.2.2.dist-info/entry_points.txt
speedtest_cloudflare_cli-0.2.2.dist-info/licenses/LICENSE
speedtest_cloudflare_cli-0.2.2.dist-info/RECORD
