Metadata-Version: 2.4
Name: speedtest-cloudflare-cli
Version: 0.2.2
Summary: Speed CLI tool to test your network connectivity
Project-URL: Homepage, https://takitsu21.github.io/speedtest/
Project-URL: Repository, https://github.com/takitsu21/speedtest
Project-URL: Documentation, https://takitsu21.github.io/speedtest/
Author-email: Dylann Batisse <dylann.batisse@protonmail.com>
License-File: LICENSE
Keywords: python
Classifier: Intended Audience :: Developers
Classifier: Programming Language :: Python
Classifier: Programming Language :: Python :: 3
Classifier: Programming Language :: Python :: 3.9
Classifier: Programming Language :: Python :: 3.10
Classifier: Programming Language :: Python :: 3.11
Classifier: Programming Language :: Python :: 3.12
Classifier: Programming Language :: Python :: 3.13
Classifier: Topic :: Software Development :: Libraries :: Python Modules
Requires-Python: <3.14,>=3.9
Requires-Dist: httpx>=0.28.0
Requires-Dist: jinja2>=3.1.6
Requires-Dist: ping3>=4.0.8
Requires-Dist: pydantic>=2.10.3
Requires-Dist: rich-click>=1.8.5
Requires-Dist: rich>=13.9.4
